scratch.v
module tff (
    output reg  q,
    output      qn,
    input       t, clk, rst
);
    always @(posedge clk) begin
        if(!rst) q <= 0;
        else begin
            if(t == 1'b1) q <= ~q;
            else  q <= q;
        end
    end
    assign qn = ~q;
endmodule

module sync_counter (
    output [3:0]    out,
    input           clk, rst, cnt
);
    
    wire i0,  i1,  i2,  i3;
    wire q0,  q1,  q2,  q3;
    wire q0n, q1n, q2n, q3n;

    assign i0 = cnt;
    assign i1 = i0 & q0;
    assign i2 = i1 & q1;
    assign i3 = i2 & q2;

    tff u0 (
        .clk(clk),
        .rst(rst),
        .t  (i0),
        .q  (q0),
        .qn (q0n)
    );
    tff u1 (
        .clk(clk),
        .rst(rst),
        .t  (i1),
        .q  (q1),
        .qn (q1n)
    );
    tff u2 (
        .clk(clk),
        .rst(rst),
        .t  (i2),
        .q  (q2),
        .qn (q2n)
    );
    tff u3 (
        .clk(clk),
        .rst(rst),
        .t  (i3),
        .q  (q3),
        .qn (q3n)
    );

    assign out = {q3,q2,q1,q0};
endmodule

module tb_sync_counter;
    reg tb_clk, tb_rst, tb_cnt;
    wire [3:0]  tb_out;
    
    initial {tb_clk, tb_rst, tb_cnt} = 3'b0;
    initial begin
        #10 tb_rst = 1;
        #20 tb_cnt = 1;
        #100 tb_cnt = 0;
    end
    always #5 tb_clk = ~tb_clk;
    initial #500 $finish;
    initial begin
        $dumpfile("build/output.vcd");
        $dumpvars(0, tb_sync_counter);
        $monitor("%d, clk=%b, rst=%b, cnt=%b, out=%b", $time, tb_clk, tb_rst, tb_cnt, tb_out);
    end

    sync_counter u1(
        .clk(tb_clk),
        .rst(tb_rst),
        .cnt(tb_cnt),
        .out(tb_out)
    );
endmodule

build/output.vcd
$date
	Sat Nov 30 20:33:52 2024
$end
$version
	Icarus Verilog
$end
$timescale
	1s
$end
$scope module tb_sync_counter $end
$var wire 4 ! tb_out [3:0] $end
$var reg 1 " tb_clk $end
$var reg 1 # tb_cnt $end
$var reg 1 $ tb_rst $end
$scope module u1 $end
$var wire 1 " clk $end
$var wire 1 # cnt $end
$var wire 1 % i0 $end
$var wire 1 & i1 $end
$var wire 1 ' i2 $end
$var wire 1 ( i3 $end
$var wire 1 $ rst $end
$var wire 1 ) q3n $end
$var wire 1 * q3 $end
$var wire 1 + q2n $end
$var wire 1 , q2 $end
$var wire 1 - q1n $end
$var wire 1 . q1 $end
$var wire 1 / q0n $end
$var wire 1 0 q0 $end
$var wire 4 1 out [3:0] $end
$scope module u0 $end
$var wire 1 " clk $end
$var wire 1 / qn $end
$var wire 1 $ rst $end
$var wire 1 % t $end
$var reg 1 0 q $end
$upscope $end
$scope module u1 $end
$var wire 1 " clk $end
$var wire 1 - qn $end
$var wire 1 $ rst $end
$var wire 1 & t $end
$var reg 1 . q $end
$upscope $end
$scope module u2 $end
$var wire 1 " clk $end
$var wire 1 + qn $end
$var wire 1 $ rst $end
$var wire 1 ' t $end
$var reg 1 , q $end
$upscope $end
$scope module u3 $end
$var wire 1 " clk $end
$var wire 1 ) qn $end
$var wire 1 $ rst $end
$var wire 1 ( t $end
$var reg 1 * q $end
$upscope $end
$upscope $end
$upscope $end
$enddefinitions $end
#0
$dumpvars
bx 1
x0
x/
x.
x-
x,
x+
x*
x)
0(
0'
0&
0%
0$
0#
0"
bx !
$end
#5
1/
1-
1+
1)
00
0.
0,
b0 !
b0 1
0*
1"
#10
0"
1$
#15
1"
#20
0"
#25
1"
#30
0"
1%
1#
#35
0/
1&
b1 !
b1 1
10
1"
#40
0"
#45
1/
0&
0-
0'
00
b10 !
b10 1
1.
1"
#50
0"
#55
1'
0/
1&
b11 !
b11 1
10
1"
#60
0"
#65
1/
0&
1-
0'
0+
0(
00
0.
b100 !
b100 1
1,
1"
#70
0"
#75
0/
1&
b101 !
b101 1
10
1"
#80
0"
#85
0(
1/
0&
0-
0'
00
b110 !
b110 1
1.
1"
#90
0"
#95
1(
1'
0/
1&
b111 !
b111 1
10
1"
#100
0"
#105
1/
0&
1-
0'
1+
0(
0)
00
0.
0,
b1000 !
b1000 1
1*
1"
#110
0"
#115
0/
1&
b1001 !
b1001 1
10
1"
#120
0"
#125
1/
0&
0-
0'
00
b1010 !
b1010 1
1.
1"
#130
0"
0%
0#
